README.md
pyproject.toml
setup.cfg
setup.py
baseapp_profiles/__init__.py
baseapp_profiles/admin.py
baseapp_profiles/apps.py
baseapp_profiles/managers.py
baseapp_profiles/middleware.py
baseapp_profiles/models.py
baseapp_profiles/permissions.py
baseapp_profiles/signals.py
baseapp_profiles.egg-info/PKG-INFO
baseapp_profiles.egg-info/SOURCES.txt
baseapp_profiles.egg-info/dependency_links.txt
baseapp_profiles.egg-info/requires.txt
baseapp_profiles.egg-info/top_level.txt
baseapp_profiles/graphql/__init__.py
baseapp_profiles/graphql/filters.py
baseapp_profiles/graphql/middleware.py
baseapp_profiles/graphql/mutations.py
baseapp_profiles/graphql/object_types.py
baseapp_profiles/graphql/queries.py
baseapp_profiles/migrations/0001_initial.py
baseapp_profiles/migrations/0002_profile_blockers_count_profile_blocking_count_and_more.py
baseapp_profiles/migrations/0003_profile_banner_image.py
baseapp_profiles/migrations/0004_profile_biography.py
baseapp_profiles/migrations/0005_profileuserrole_status.py
baseapp_profiles/migrations/0006_alter_profile_name.py
baseapp_profiles/migrations/__init__.py
baseapp_profiles/tests/__init__.py
baseapp_profiles/tests/conftest.py
baseapp_profiles/tests/factories.py
baseapp_profiles/tests/test_get_queries.py
baseapp_profiles/tests/test_graphql_mutations_delete.py
baseapp_profiles/tests/test_graphql_mutations_update.py
baseapp_profiles/tests/test_middleware.py
baseapp_profiles/tests/test_migration_health_check.py
baseapp_profiles/tests/test_url_path.py
baseapp_profiles/tests/utils.py
testproject/__init__.py
testproject/graphql.py
testproject/settings.py
testproject/setup.py
testproject/urls.py
testproject/wsgi.py
testproject/testapp/__init__.py
testproject/testapp/admin.py
testproject/testapp/apps.py
testproject/testapp/models.py
testproject/testapp/migrations/0001_initial.py
testproject/testapp/migrations/0002_auto_20160321_1909.py
testproject/testapp/migrations/0003_auto_20160725_2001.py
testproject/testapp/migrations/0004_auto_20160811_1614.py
testproject/testapp/migrations/0005_user_password_changed_date.py
testproject/testapp/migrations/0006_alter_user_id.py
