Metadata-Version: 2.1
Name: baseapp-profiles
Version: 0.3.15
Summary: BaseApp Profiles
Home-page: https://github.com/silverlogic/baseapp-backend
Author: The SilverLogic
Author-email: dev@tsl.io
License: BSD-3-Clause  # Example license
Platform: UNKNOWN
Requires-Python: >=3.6
